MANIFEST.in
README.rst
config.spec
defaults.config
setup.py
prego/__init__.py
prego/assert_that.py
prego/assertion.py
prego/command.py
prego/config.py
prego/console.py
prego/const.py
prego/debian.py
prego/exc.py
prego/gvars.py
prego/item.py
prego/net.py
prego/runner.py
prego/shell.py
prego/task.py
prego/testcase.py
prego/tools.py
prego.egg-info/PKG-INFO
prego.egg-info/SOURCES.txt
prego.egg-info/dependency_links.txt
prego.egg-info/entry_points.txt
prego.egg-info/requires.txt
prego.egg-info/top_level.txt
test/__init__.py
test/context_tests.py
test/dist_test.py
test/integration_tests.py
test/interpolation_tests.py
test/plugin_debian_tests.py
test/plugin_tests.py
test/report_tests.py
test/unit_tests.py