Metadata-Version: 1.1
Name: prego
Version: 0.20150306
Summary: System test framework over POSIX shells
Home-page: https://bitbucket.org/arco_group/prego
Author: David Villa Alises
Author-email: David.Villa@gmail.com
License: GPLv3
Platform: UNKNOWN
Classifier: Intended Audience :: Developers
Classifier: License :: OSI Approved :: GNU General Public License v3 or later (GPLv3+)
Classifier: Operating System :: OS Independent
Classifier: Programming Language :: Python
Classifier: Topic :: Software Development
Classifier: Topic :: Software Development :: Quality Assurance
Classifier: Topic :: Software Development :: Testing
